LICENSE
MANIFEST.in
README
README.md
setup.cfg
setup.py
revo_utils/__init__.py
revo_utils/utils.py
revo_utils.egg-info/PKG-INFO
revo_utils.egg-info/SOURCES.txt
revo_utils.egg-info/dependency_links.txt
revo_utils.egg-info/requires.txt
revo_utils.egg-info/top_level.txt